[
  {
    "id": 1,
    "eventId": 1,
    "name": "活動徽章",
    "flavorText": "可至活動交換所交換道具。"
  },
  {
    "id": 2,
    "eventId": 2,
    "name": "活動徽章",
    "flavorText": "可至活動交換所交換道具。"
  },
  {
    "id": 3,
    "eventId": 3,
    "name": "活動徽章",
    "flavorText": "可至活動交換所交換道具。"
  },
  {
    "id": 4,
    "eventId": 4,
    "name": "活動徽章",
    "flavorText": "可至活動交換所交換道具。"
  },
  {
    "id": 5,
    "eventId": 5,
    "name": "活動徽章",
    "flavorText": "可至活動交換所交換道具。"
  },
  {
    "id": 6,
    "eventId": 6,
    "name": "活動徽章",
    "flavorText": "可至活動交換所交換道具。"
  },
  {
    "id": 7,
    "eventId": 7,
    "name": "活動徽章",
    "flavorText": "可至活動交換所交換道具。"
  },
  {
    "id": 8,
    "eventId": 8,
    "name": "活動徽章",
    "flavorText": "可至活動交換所交換道具。"
  },
  {
    "id": 9,
    "eventId": 9,
    "name": "活動徽章",
    "flavorText": "可至活動交換所交換道具。"
  },
  {
    "id": 10,
    "eventId": 10,
    "name": "活動徽章",
    "flavorText": "可至活動交換所交換道具。"
  },
  {
    "id": 11,
    "eventId": 11,
    "name": "活動徽章",
    "flavorText": "可至活動交換所交換道具。"
  },
  {
    "id": 12,
    "eventId": 12,
    "name": "活動徽章",
    "flavorText": "可至活動交換所交換道具。"
  },
  {
    "id": 13,
    "eventId": 13,
    "name": "活動徽章",
    "flavorText": "可至活動交換所交換道具。"
  },
  {
    "id": 14,
    "eventId": 14,
    "name": "活動徽章",
    "flavorText": "可至活動交換所交換道具。"
  },
  {
    "id": 15,
    "eventId": 15,
    "name": "活動徽章",
    "flavorText": "可至活動交換所交換道具。"
  },
  {
    "id": 16,
    "eventId": 16,
    "name": "活動徽章",
    "flavorText": "可至活動交換所交換道具。"
  },
  {
    "id": 17,
    "eventId": 17,
    "name": "活動徽章",
    "flavorText": "可至活動交換所交換道具。"
  },
  {
    "id": 18,
    "eventId": 18,
    "name": "活動徽章",
    "flavorText": "可至活動交換所交換道具。"
  },
  {
    "id": 19,
    "eventId": 19,
    "name": "活動徽章",
    "flavorText": "可至活動交換所交換道具。"
  },
  {
    "id": 20,
    "eventId": 20,
    "name": "活動徽章",
    "flavorText": "可至活動交換所交換道具。"
  },
  {
    "id": 21,
    "eventId": 21,
    "name": "活動徽章",
    "flavorText": "可至活動交換所交換道具。"
  },
  {
    "id": 22,
    "eventId": 22,
    "name": "活動徽章",
    "flavorText": "可至活動交換所交換道具。"
  },
  {
    "id": 23,
    "eventId": 23,
    "name": "活動徽章",
    "flavorText": "可至活動交換所交換道具。"
  },
  {
    "id": 24,
    "eventId": 24,
    "name": "活動徽章",
    "flavorText": "可至活動交換所交換道具。"
  }
]