[
  {
    "id": 3,
    "liveMissionPeriodId": 3,
    "costumeName": "次文化男孩風格",
    "character3dId1": 32,
    "character3dId2": 33,
    "maleAssetbundleName": "cos0011_body",
    "femaleAssetbundleName": "cos0012_body"
  },
  {
    "id": 4,
    "liveMissionPeriodId": 4,
    "costumeName": "毛茸茸防雪大衣",
    "character3dId1": 47,
    "character3dId2": 48,
    "maleAssetbundleName": "cos0040_body",
    "femaleAssetbundleName": "cos0041_body"
  },
  {
    "id": 5,
    "liveMissionPeriodId": 5,
    "costumeName": "女僕／管家",
    "character3dId1": 68,
    "character3dId2": 69,
    "maleAssetbundleName": "cos0048_body",
    "femaleAssetbundleName": "cos0049_body"
  },
  {
    "id": 6,
    "liveMissionPeriodId": 6,
    "costumeName": "「甜點」服裝",
    "character3dId1": 144,
    "character3dId2": 145,
    "maleAssetbundleName": "cos0058_body",
    "femaleAssetbundleName": "cos0059_body"
  },
  {
    "id": 7,
    "liveMissionPeriodId": 7,
    "costumeName": "可愛虎風格／帥氣虎風格",
    "character3dId1": 10001,
    "character3dId2": 10002,
    "maleAssetbundleName": "cos0068_body",
    "femaleAssetbundleName": "cos0069_body"
  },
  {
    "id": 8,
    "liveMissionPeriodId": 8,
    "costumeName": "「近未來」服裝",
    "character3dId1": 167,
    "character3dId2": 168,
    "maleAssetbundleName": "cos0076_body",
    "femaleAssetbundleName": "cos0077_body"
  },
  {
    "id": 9,
    "liveMissionPeriodId": 9,
    "costumeName": "「怪盜」服裝",
    "character3dId1": 188,
    "character3dId2": 189,
    "maleAssetbundleName": "cos0086_body",
    "femaleAssetbundleName": "cos0087_body"
  },
  {
    "id": 10,
    "liveMissionPeriodId": 10,
    "costumeName": "「魔法」服裝",
    "character3dId1": 207,
    "character3dId2": 208,
    "maleAssetbundleName": "cos0096_body",
    "femaleAssetbundleName": "cos0097_body"
  },
  {
    "id": 11,
    "liveMissionPeriodId": 11,
    "costumeName": "「餐廳」服裝",
    "character3dId1": 227,
    "character3dId2": 228,
    "maleAssetbundleName": "cos0104_body",
    "femaleAssetbundleName": "cos0105_body"
  },
  {
    "id": 12,
    "liveMissionPeriodId": 12,
    "costumeName": "「海盜」服裝",
    "character3dId1": 254,
    "character3dId2": 255,
    "maleAssetbundleName": "cos0115_body",
    "femaleAssetbundleName": "cos0114_body"
  },
  {
    "id": 13,
    "liveMissionPeriodId": 13,
    "costumeName": "「Animal」服裝",
    "character3dId1": 277,
    "character3dId2": 278,
    "maleAssetbundleName": "cos0122_body",
    "femaleAssetbundleName": "cos0123_body"
  },
  {
    "id": 14,
    "liveMissionPeriodId": 14,
    "costumeName": "「睡衣」服裝",
    "character3dId1": 306,
    "character3dId2": 307,
    "maleAssetbundleName": "cos0130_body",
    "femaleAssetbundleName": "cos0131_body"
  }
]