[
  {
    "homeBannerId": 18,
    "seq": 9999,
    "homeBannerType": "general",
    "name": "新手指南",
    "assetbundleName": "banner_beginners_guide",
    "transitionDestinationType": "information",
    "transitionDestinationId": 10003,
    "startAt": 1632967200000,
    "endAt": 4102415999000
  },
  {
    "homeBannerId": 48,
    "seq": 9998,
    "homeBannerType": "general",
    "name": "Welcome LIVE橫幅",
    "assetbundleName": "banner_welcomelive",
    "transitionDestinationType": "virtual_live",
    "transitionDestinationId": 20001,
    "startAt": 1635750000000,
    "endAt": 4102415999000
  },
  {
    "homeBannerId": 199,
    "seq": 200,
    "homeBannerType": "general",
    "name": "[2021/08]高階任務通行證",
    "assetbundleName": "banner_premiummissionpass_2021_08",
    "transitionDestinationType": "billing_shop_for_live_mission_pass",
    "startAt": 1659888000000,
    "endAt": 1661961599000
  },
  {
    "homeBannerId": 208,
    "seq": 100,
    "homeBannerType": "event",
    "name": "[活動]對美人魚充滿憧憬",
    "assetbundleName": "event_mermaid_2021",
    "transitionDestinationType": "event",
    "transitionDestinationId": 32,
    "startAt": 1660978800000,
    "endAt": 1661929199000
  },
  {
    "homeBannerId": 210,
    "seq": 110,
    "homeBannerType": "general",
    "name": "Wonderlands×Showtime第5次巡迴_常態招募橫幅",
    "assetbundleName": "banner_gacha112",
    "transitionDestinationType": "gacha",
    "transitionDestinationId": 112,
    "startAt": 1660978800000,
    "endAt": 1661929199000
  },
  {
    "homeBannerId": 10005,
    "seq": 132,
    "homeBannerType": "general",
    "name": "七彩通行证",
    "assetbundleName": "banner_colorfulpass",
    "transitionDestinationType": "billing_shop_for_colorful_pass",
    "startAt": 1646280000000,
    "endAt": 4094294399000
  }
]