[
  {
    "homeBannerId": 18,
    "seq": 9999,
    "homeBannerType": "general",
    "name": "新手指南",
    "assetbundleName": "banner_beginners_guide",
    "transitionDestinationType": "information",
    "transitionDestinationId": 10003,
    "startAt": 1632967200000,
    "endAt": 4102415999000
  },
  {
    "homeBannerId": 48,
    "seq": 9998,
    "homeBannerType": "general",
    "name": "Welcome LIVE橫幅",
    "assetbundleName": "banner_welcomelive",
    "transitionDestinationType": "virtual_live",
    "transitionDestinationId": 20001,
    "startAt": 1635750000000,
    "endAt": 4102415999000
  },
  {
    "homeBannerId": 237,
    "seq": 50,
    "homeBannerType": "general",
    "name": "[一週年紀念]紀念選擇招募",
    "assetbundleName": "banner_gacha124",
    "transitionDestinationType": "gacha",
    "transitionDestinationId": 124,
    "startAt": 1664467200000,
    "endAt": 1667199599000
  },
  {
    "homeBannerId": 238,
    "seq": 150,
    "homeBannerType": "general",
    "name": "一週年紀念水晶商店",
    "assetbundleName": "banner_1st_anniversary_shop",
    "transitionDestinationType": "billing_shop_for_jewel",
    "startAt": 1664467200000,
    "endAt": 1665464399000
  },
  {
    "homeBannerId": 240,
    "seq": 140,
    "homeBannerType": "general",
    "name": "[一週年紀念]免費10連票券招募",
    "assetbundleName": "banner_gacha123",
    "transitionDestinationType": "gacha",
    "transitionDestinationId": 123,
    "startAt": 1664481600000,
    "endAt": 1666022399000
  },
  {
    "homeBannerId": 241,
    "seq": 20,
    "homeBannerType": "general",
    "name": "[2021/10]高階任務通行證（月初優先度UP用）",
    "assetbundleName": "banner_premiummissionpass_2021_10",
    "transitionDestinationType": "billing_shop_for_live_mission_pass",
    "startAt": 1664553600000,
    "endAt": 1667231999000
  },
  {
    "homeBannerId": 242,
    "seq": 160,
    "homeBannerType": "general",
    "name": "再次販售「次文化男孩風格」",
    "assetbundleName": "banner_costume_resale_2021_10",
    "transitionDestinationType": "billing_shop_for_jewel",
    "startAt": 1664553600000,
    "endAt": 1667231999000
  },
  {
    "homeBannerId": 243,
    "seq": 30,
    "homeBannerType": "general",
    "name": "[一週年紀念]七彩慶典招募",
    "assetbundleName": "banner_gacha125",
    "transitionDestinationType": "gacha",
    "transitionDestinationId": 125,
    "startAt": 1664607600000,
    "endAt": 1664953199000
  },
  {
    "homeBannerId": 244,
    "seq": 100,
    "homeBannerType": "event",
    "name": "[活動]混亂的粉絲感謝祭！",
    "assetbundleName": "event_scramble_2021",
    "transitionDestinationType": "event",
    "transitionDestinationId": 35,
    "startAt": 1664607600000,
    "endAt": 1665471599000
  },
  {
    "homeBannerId": 245,
    "seq": 40,
    "homeBannerType": "general",
    "name": "高級禮物招募（虛擬歌手）",
    "assetbundleName": "banner_gacha126",
    "transitionDestinationType": "gacha",
    "transitionDestinationId": 126,
    "startAt": 1664607600000,
    "endAt": 1664866740000
  },
  {
    "homeBannerId": 246,
    "seq": 40,
    "homeBannerType": "general",
    "name": "高級禮物招募（Leo/need）",
    "assetbundleName": "banner_gacha127",
    "transitionDestinationType": "gacha",
    "transitionDestinationId": 127,
    "startAt": 1664694000000,
    "endAt": 1664953140000
  },
  {
    "homeBannerId": 247,
    "seq": 40,
    "homeBannerType": "general",
    "name": "高級禮物招募（MORE MORE JUMP！）",
    "assetbundleName": "banner_gacha128",
    "transitionDestinationType": "gacha",
    "transitionDestinationId": 128,
    "startAt": 1664780400000,
    "endAt": 1665039540000
  },
  {
    "homeBannerId": 254,
    "seq": 160,
    "homeBannerType": "general",
    "name": "[桐谷遙]HAPPY BIRTHDAY LIVE",
    "assetbundleName": "banner_virtuallive98",
    "transitionDestinationType": "virtual_live",
    "transitionDestinationId": 98,
    "startAt": 1664780400000,
    "endAt": 1665039599000
  },
  {
    "homeBannerId": 10005,
    "seq": 132,
    "homeBannerType": "general",
    "name": "七彩通行证",
    "assetbundleName": "banner_colorfulpass",
    "transitionDestinationType": "billing_shop_for_colorful_pass",
    "startAt": 1646280000000,
    "endAt": 4094294399000
  }
]